CHANGES.txt
COPYRIGHT.txt
LICENSE.txt
setup.py
van/__init__.py
van.potomo.egg-info/PKG-INFO
van.potomo.egg-info/SOURCES.txt
van.potomo.egg-info/dependency_links.txt
van.potomo.egg-info/entry_points.txt
van.potomo.egg-info/namespace_packages.txt
van.potomo.egg-info/requires.txt
van.potomo.egg-info/top_level.txt
van.potomo.egg-info/zip-safe
van/potomo/README.txt
van/potomo/__init__.py