Metadata-Version: 1.1
Name: van.potomo
Version: 2.0
Summary: PO to MO build time compiler
Home-page: http://pypi.python.org/pypi/van.potomo
Author: Vanguardistas LLC
Author-email: zope-dev@zope.org
License: ZPL 2.1
Platform: UNKNOWN
Classifier: Intended Audience :: Developers
Classifier: License :: OSI Approved :: Zope Public License
Classifier: Framework :: Setuptools Plugin
Classifier: Programming Language :: Python
Classifier: Development Status :: 5 - Production/Stable
Classifier: Operating System :: OS Independent
Classifier: Topic :: Software Development :: Build Tools
Classifier: Programming Language :: Python :: 3
Classifier: Programming Language :: Python :: 2
